uedge/VERSION
uedge/__init__.py
uedge/aphpy.cpython-310-x86_64-linux-gnu.so
uedge/apipy.cpython-310-x86_64-linux-gnu.so
uedge/bbbpy.cpython-310-x86_64-linux-gnu.so
uedge/cdf4.py
uedge/checkver.py
uedge/compy.cpython-310-x86_64-linux-gnu.so
uedge/convert1.py
uedge/filelists.py
uedge/flxpy.cpython-310-x86_64-linux-gnu.so
uedge/grdpy.cpython-310-x86_64-linux-gnu.so
uedge/gridue.py
uedge/hdf5.py
uedge/nclpy.cpython-310-x86_64-linux-gnu.so
uedge/rundt.py
uedge/sources.py
uedge/svrpy.cpython-310-x86_64-linux-gnu.so
uedge/uedge.py
uedge/uedgeC.cpython-310-x86_64-linux-gnu.so
uedge/uedge_lists.py
uedge/uedgeplots.py
uedge/wdfpy.cpython-310-x86_64-linux-gnu.so
uedge-8.1.2.post1.data/scripts/bas2py
uedge-8.1.2.post1.data/scripts/hdf52pdb
uedge-8.1.2.post1.data/scripts/pdb2hdf5
uedge.libs/libgfortran-040039e1.so.5.0.0
uedge.libs/libquadmath-96973f99.so.0.0.0
uedge-8.1.2.post1.dist-info/METADATA
uedge-8.1.2.post1.dist-info/WHEEL
uedge-8.1.2.post1.dist-info/top_level.txt
uedge-8.1.2.post1.dist-info/RECORD
uedge-8.1.2.post1.dist-info/licenses/LICENSE
uedge-8.1.2.post1.dist-info/licenses/NOTICE
