Metadata-Version: 2.4
Name: uedge
Version: 8.1.2.post1
Summary: 2D Fluid simulation of plasma and neutrals in magnetic fusion devices
Author: Tom Rognlien
Maintainer-email: Bill Meyer <meyer8@llnl.gov>, Andreas Holm <holm10@llnl.gov>
Project-URL: Homepage, https://github.com/LLNL/UEDGE/
Project-URL: Repository, https://github.com/LLNL/UEDGE.git
Project-URL: Issues, https://github.com/LLNL/UEDGE/issues
Keywords: plasma,fusion,tokamak,edge-plasma,scrape-off layer,multi-fluid
Classifier: Intended Audience :: Science/Research
Classifier: License :: OSI Approved :: GNU Lesser General Public License v2 or later (LGPLv2+)
Classifier: Operating System :: Unix
Classifier: Operating System :: MacOS :: MacOS X
Classifier: Programming Language :: Fortran
Classifier: Programming Language :: Python
Classifier: Programming Language :: Python :: 3
Classifier: Topic :: Scientific/Engineering :: Physics
Requires-Python: >=3.8
License-File: LICENSE
License-File: NOTICE
Requires-Dist: forthon>=0.10.7
Requires-Dist: numpy
Provides-Extra: ueplot
Requires-Dist: matplotlib; extra == "ueplot"
Requires-Dist: scipy; extra == "ueplot"
Requires-Dist: scikit-image; extra == "ueplot"
Requires-Dist: h5py; extra == "ueplot"
Dynamic: license-file
